slack_models/__init__.py
slack_models/_models.py
slack_models/_utils.py
slack_models/py.typed
slack_models-1.1.0.dist-info/METADATA
slack_models-1.1.0.dist-info/WHEEL
slack_models-1.1.0.dist-info/licenses/LICENSE
slack_models-1.1.0.dist-info/RECORD
