Metadata-Version: 2.4
Name: slack-models
Version: 1.1.0
Summary: Pydantic Models for working with the Slack API
Author-email: "Gavin M. Roy" <gavinr@aweber.com>
License-Expression: BSD-3-Clause
License-File: LICENSE
Classifier: Development Status :: 4 - Beta
Classifier: License :: OSI Approved :: BSD License
Classifier: Programming Language :: PL/SQL
Classifier: Programming Language :: Python :: 3
Classifier: Programming Language :: Python :: 3.12
Classifier: Programming Language :: Python :: 3.13
Classifier: Programming Language :: SQL
Classifier: Topic :: Database
Classifier: Topic :: Software Development :: Libraries
Classifier: Typing :: Typed
Requires-Python: >=3.12
Requires-Dist: pydantic<3,>=2.11.3
Provides-Extra: dev
Requires-Dist: build<2,>=1.2.2; extra == 'dev'
Requires-Dist: coverage<8,>=7.6.10; extra == 'dev'
Requires-Dist: mypy; extra == 'dev'
Requires-Dist: pre-commit<5,>=4.1.0; extra == 'dev'
Requires-Dist: pytest; extra == 'dev'
Requires-Dist: pytest-cov; extra == 'dev'
Requires-Dist: ruff<0.12.0,>=0.9.5; extra == 'dev'
Provides-Extra: docs
Requires-Dist: black; extra == 'docs'
Requires-Dist: griffe-pydantic; extra == 'docs'
Requires-Dist: mkdocs-material<10,>9.5; extra == 'docs'
Requires-Dist: mkdocs<2,>=1.5; extra == 'docs'
Requires-Dist: mkdocstrings-python-xref<2,>=1.6; extra == 'docs'
Requires-Dist: mkdocstrings[python]<0.27,>=0.26; extra == 'docs'
